<?xml version="1.0" encoding="UTF-8"?>
<gui xmlns="uri:hui" title="Opsætning">
  <dock url="settings.gui" name="dock">
    <tabs below="true" small="true">
      <tab background="light">
        <toolbar>
          <icon icon="common/settings" text="Settings" click="dock.setUrl('settings.gui')"/>
          <icon icon="common/time" text="Jobs" click="dock.setUrl('scheduler.gui')"/>
          <icon icon="common/search" text="Surveillance" click="dock.setUrl('surveillance.gui')"/>
          <divider/>
          <icon icon="common/object" text="Model" click="dock.setUrl('model.gui')"/>
          <icon icon="common/image" text="Images" click="dock.setUrl('images.gui')"/>
          <icon icon="common/user" text="Users" click="dock.setUrl('users.gui')"/>
          <icon icon="common/search" text="Indices" click="dock.setUrl('indices.gui')"/>
          <divider/>
          <icon icon="common/user" text="Integration" click="dock.setUrl('integration.gui')"/>
          <icon icon="common/internet" text="Internet addresses" click="dock.setUrl('internetaddresses.gui')"/>
        </toolbar>
      </tab>
    </tabs>
  </dock>
</gui>